{
    "administrador": {
        "login": "admin",
        "senha": "123456"
    },
    "carros": [
        {
            "carro_id": 1,
            "epc": "E2000017221101241890547C",
            "modelo": "formula 1",
            "cor": "#54545f",
            "marca": "Mercedes",
            "num": "1"
        },
        {
            "carro_id": 2,
            "epc": "E20000172211011718905474",
            "modelo": "formula 1",
            "cor": "#a19797",
            "marca": "Mercedes",
            "num": "2"
        },
        {
            "carro_id": 3,
            "epc": "E2000017221101321890548C",
            "modelo": "formula 1",
            "cor": "#0a0797",
            "marca": "Red Bull",
            "num": "3"
        },
        {
            "carro_id": 4,
            "epc": "E20000172211012518905484",
            "modelo": "formula 1",
            "cor": "#120995",
            "marca": "Red Bull",
            "num": "4"
        },
        {
            "carro_id": 5,
            "epc": "E20000172211013118905493",
            "modelo": "formula 1",
            "cor": "#e70404",
            "marca": "Ferrari",
            "num": "5"
        }
    ],
    "pilotos": [
        {
            "piloto_id": 1,
            "nome": "Mariana",
            "apelido": "Mari",
            "nacionalidade": "Brasil",
            "nascimento": "00/00/0000",
            "carro_id": 1,
            "equipe_id": 1,
            "ativo": true
        },
        {
            "piloto_id": 2,
            "nome": "Elisangêla",
            "apelido": "Eli",
            "nacionalidade": "Brasil",
            "nascimento": "00/00/0000",
            "carro_id": 2,
            "equipe_id": 1,
            "ativo": true
        },
        {
            "piloto_id": 3,
            "nome": "Anderson",
            "apelido": "And",
            "nacionalidade": "BRASIL",
            "nascimento": "00/00/0000",
            "carro_id": 3,
            "equipe_id": 2,
            "ativo": true
        },
        {
            "piloto_id": 4,
            "nome": "Antonio",
            "apelido": "Prof",
            "nacionalidade": "Brasil",
            "nascimento": "00/00/0000",
            "carro_id": 4,
            "equipe_id": 2,
            "ativo": true
        },
        {
            "piloto_id": 5,
            "nome": "Tales",
            "apelido": "tales",
            "nacionalidade": "brasil",
            "nascimento": "00/00/0000",
            "carro_id": 5,
            "equipe_id": 3,
            "ativo": true
        }
    ],
    "equipes": [
        {
            "equipe_id": 1,
            "nome": "Mercedes",
            "apelido": "Mer",
            "nacionalidade": "Alemanha",
            "ano": "01/01/1920",
            "pontos": 0
        },
        {
            "equipe_id": 2,
            "nome": "Red Bull",
            "apelido": "RB",
            "nacionalidade": "Austria",
            "ano": "01/01/1920",
            "pontos": 0
        },
        {
            "equipe_id": 3,
            "nome": "Ferrari",
            "apelido": "Fer",
            "nacionalidade": "Italia",
            "ano": "01/01/1920",
            "pontos": 0
        }
    ],
    "circuitos": [
        {
            "circuito_id": 1,
            "nome": "Monza",
            "pais": "Italia",
            "tempoMinimoVolta": 30,
            "recorde": "00:30:000",
            "autor": "Elisangêla"
        }
    ],
    "corridas": [
        {
            "corrida_id": 1,
            "quantidadeDeVoltas": 5,
            "qualificatoriaDuracao": "05:00:000",
            "circuito_id": 1,
            "qualificatoriaCompleta": 1,
            "corridaCompleta": 0,
            "pilotos": [
                {
                    "piloto_id": 1,
                    "carro_epc": "E2000017221101241890547C"
                },
                {
                    "piloto_id": 2,
                    "carro_epc": "E20000172211011718905474"
                },
                {
                    "piloto_id": 3,
                    "carro_epc": "E2000017221101321890548C"
                },
                {
                    "piloto_id": 4,
                    "carro_epc": "E20000172211012518905484"
                },
                {
                    "piloto_id": 5,
                    "carro_epc": "E20000172211013118905493"
                }
            ],
            "qualificatoria": {
                "E2000017221101241890547C": {
                    "piloto_id": 1,
                    "carro_epc": "E2000017221101241890547C",
                    "tempo_menor": "00:30:003",
                    "timestamp": 1619555468.452,
                    "voltas": 5,
                    "tempo_menor_timestamp": 30.003000020980835
                },
                "E20000172211011718905474": {
                    "piloto_id": 2,
                    "carro_epc": "E20000172211011718905474",
                    "tempo_menor": "00:30:000",
                    "timestamp": 1619555475.439,
                    "voltas": 5,
                    "tempo_menor_timestamp": 30.000999927520752
                },
                "E2000017221101321890548C": {
                    "piloto_id": 3,
                    "carro_epc": "E2000017221101321890548C",
                    "tempo_menor": "00:30:001",
                    "timestamp": 1619555480.635,
                    "voltas": 5,
                    "tempo_menor_timestamp": 30.00100016593933
                },
                "E20000172211012518905484": {
                    "piloto_id": 4,
                    "carro_epc": "E20000172211012518905484",
                    "tempo_menor": "00:30:005",
                    "timestamp": 1619555487.239,
                    "voltas": 5,
                    "tempo_menor_timestamp": 30.005000114440918
                },
                "E20000172211013118905493": {
                    "piloto_id": 5,
                    "carro_epc": "E20000172211013118905493",
                    "tempo_menor": "00:30:010",
                    "timestamp": 1619555463.96,
                    "voltas": 4,
                    "tempo_menor_timestamp": 30.01099991798401
                }
            },
            "classificacao": {
                "E2000017221101241890547C": {
                    "piloto_id": 1,
                    "carro_epc": "E2000017221101241890547C",
                    "tempo_total": "9:99:999",
                    "tempo_menor": "9:99:999",
                    "tempo_atual": "9:99:999",
                    "timestamp": 0,
                    "voltas": 0,
                    "pits": 0,
                    "pos_inicial": 3
                },
                "E20000172211011718905474": {
                    "piloto_id": 2,
                    "carro_epc": "E20000172211011718905474",
                    "tempo_total": "9:99:999",
                    "tempo_menor": "9:99:999",
                    "tempo_atual": "9:99:999",
                    "timestamp": 0,
                    "voltas": 0,
                    "pits": 0,
                    "pos_inicial": 1
                },
                "E2000017221101321890548C": {
                    "piloto_id": 3,
                    "carro_epc": "E2000017221101321890548C",
                    "tempo_total": "9:99:999",
                    "tempo_menor": "9:99:999",
                    "tempo_atual": "9:99:999",
                    "timestamp": 0,
                    "voltas": 0,
                    "pits": 0,
                    "pos_inicial": 2
                },
                "E20000172211012518905484": {
                    "piloto_id": 4,
                    "carro_epc": "E20000172211012518905484",
                    "tempo_total": "9:99:999",
                    "tempo_menor": "9:99:999",
                    "tempo_atual": "9:99:999",
                    "timestamp": 0,
                    "voltas": 0,
                    "pits": 0,
                    "pos_inicial": 4
                },
                "E20000172211013118905493": {
                    "piloto_id": 5,
                    "carro_epc": "E20000172211013118905493",
                    "tempo_total": "9:99:999",
                    "tempo_menor": "9:99:999",
                    "tempo_atual": "9:99:999",
                    "timestamp": 0,
                    "voltas": 0,
                    "pits": 0,
                    "pos_inicial": 5
                }
            },
            "classificacaoDuracao": "00:00:00"
        }
    ],
    "tags": {
        "last": {}
    },
    "corrida_ativa": 1
}